zimra/__init__.py
zimra-0.0.4.dist-info/METADATA
zimra-0.0.4.dist-info/WHEEL
zimra-0.0.4.dist-info/top_level.txt
zimra-0.0.4.dist-info/RECORD
