Metadata-Version: 2.4
Name: zimra
Version: 0.0.4
Summary: Unofficial Python wrapper for the ZIMRA FDMS API by Tarmica Chiwara
Home-page: https://github.com/lordskyzw/zimra
Author: Tarmica Chiwara
Author-email: Tarmica Chiwara <tarimicac@gmail.com>
License: MIT
Project-URL: Repository, https://github.com/lordskyzw/zimra
Keywords: fiscalisation,api,automation,zimra,opensource
Classifier: Programming Language :: Python :: 3
Classifier: License :: OSI Approved :: MIT License
Classifier: Operating System :: OS Independent
Requires-Python: >=3.12
Requires-Dist: requests>=2.25.0
Requires-Dist: colorama>=0.4.3
Requires-Dist: requests_toolbelt>=0.9.1
Dynamic: author
Dynamic: home-page
Dynamic: requires-python
